gor_logger/__init__.py
gor_logger/gor_logger.py
gor_logger-1.0.0.dist-info/LICENSE.txt
gor_logger-1.0.0.dist-info/METADATA
gor_logger-1.0.0.dist-info/WHEEL
gor_logger-1.0.0.dist-info/top_level.txt
gor_logger-1.0.0.dist-info/RECORD
