Metadata-Version: 2.1
Name: gor-logger
Version: 1.0.0
Summary: UNKNOWN
Home-page: UNKNOWN
Author: Shivam Nagar
Author-email: shivam.n@greyorange.com
License: UNKNOWN
Platform: UNKNOWN
Classifier: Operating System :: POSIX :: Linux
Classifier: Programming Language :: Python :: 3.9
License-File: LICENSE.txt
